pulpcore_releases/__init__.py
pulpcore_releases/prc.py
pulpcore_releases-0.1.0b0.dist-info/entry_points.txt
pulpcore_releases-0.1.0b0.dist-info/WHEEL
pulpcore_releases-0.1.0b0.dist-info/METADATA
pulpcore_releases-0.1.0b0.dist-info/RECORD
