Metadata-Version: 2.1
Name: pulpcore-releases
Version: 0.1.0b0
Summary: Pulpcore - Releases & Compatibility
License: GPL-2.0-or-later
Author: Fabricio Aguiar
Author-email: fabricio.aguiar@gmail.com
Requires-Python: >=3.6
Classifier: License :: OSI Approved :: GNU General Public License v2 or later (GPLv2+)
Classifier: Programming Language :: Python :: 3
Classifier: Programming Language :: Python :: 3.6
Classifier: Programming Language :: Python :: 3.7
Classifier: Programming Language :: Python :: 3.8
Requires-Dist: aiohttp (>=3.6.2,<4.0.0)
Requires-Dist: packaging (>=20.4,<21.0)
